{"_id":"8594aee0-4ca8-11e7-b01e-ed76896ffcf4","_parent":"no-such-filed-error","reply":"","replyTarget":"","name":"Eula","email":"8c03e3950c40eb2a885c303989471901","url":"http://virilityexreviewed.com/","message":"Wow! This could be one particular of the most helpful \r\nblogs We have ever arrive across on this subject.\r\nActually Fantastic. I am also a specialist in this topic therefore I can understand your \r\neffort.","path":"2016/10/21/no-such-filed-error/","date":"2017-06-09T00:13:54.141Z"}